AUTHORS.rst
CONTRIBUTING.rst
HISTORY.rst
LICENSE
MANIFEST.in
README.rst
requirements.txt
requirements_dev.txt
setup.cfg
setup.py
docs/Makefile
docs/authors.rst
docs/conf.py
docs/contributing.rst
docs/history.rst
docs/index.rst
docs/installation.rst
docs/make.bat
docs/readme.rst
docs/usage.rst
parrot_api/core/__init__.py
parrot_api/core/common.py
parrot_api/core/logging.py
parrot_api/core/memos.py
parrot_api/core/requests.py
parrot_api/core/server.py
parrot_api/core/settings.py
parrot_api/core/auth/__init__.py
parrot_api/core/auth/jwt.py
parrot_api/core/auth/oauth.py
parrot_api/core/auth/providers/__init__.py
parrot_api/core/auth/providers/auth0.py
parrot_api/core/auth/providers/okta.py
parrot_api_core.egg-info/PKG-INFO
parrot_api_core.egg-info/SOURCES.txt
parrot_api_core.egg-info/dependency_links.txt
parrot_api_core.egg-info/not-zip-safe
parrot_api_core.egg-info/requires.txt
parrot_api_core.egg-info/top_level.txt
tests/__init__.py
tests/conftest.py
tests/test_async_requests.py
tests/test_common.py
tests/test_logs.py
tests/test_server.py
tests/test_settings.py
tests/test_sync_requests.py
tests/auth/__init__.py
tests/auth/conftest.py
tests/auth/test_jwt.py
tests/auth/test_oauth_async.py
tests/auth/mocks/public_keys.json
tests/auth/mocks/signing_key.json
tests/auth/mocks/schemas/test.yaml
tests/auth/mocks/settings/app.json
tests/mocks/async_app/__init__.py
tests/mocks/async_app/schemas/example.yaml
tests/mocks/example_app/__init__.py
tests/mocks/example_app/routes.py
tests/mocks/example_app/schemas/example.yaml
tests/mocks/example_package/__init__.py
tests/mocks/example_package/example.py
tests/mocks/example_package/schemas/test.yaml
tests/mocks/invalid_settings/env/app.json
tests/mocks/invalid_settings/secrets/app.json
tests/mocks/stringified_settings/env/app.json
tests/mocks/test_settings/env/app.json
tests/mocks/test_settings/secrets/app.json
tests/mocks/test_settings/test/app.json
tests/mocks/test_settings/test/celery.json