Metadata-Version: 2.1
Name: parrot-api-core
Version: 0.1.20
Summary: Python API Project Framework
Home-page: https://github.com/perrystallings/parrot_api_core
Author: Perry Stallings
Author-email: astal01@gmail.com
License: MIT license
Keywords: parrot_api_core
Classifier: Development Status :: 2 - Pre-Alpha
Classifier: Intended Audience :: Developers
Classifier: License :: OSI Approved :: MIT License
Classifier: Natural Language :: English
Classifier: Programming Language :: Python :: 3
Classifier: Programming Language :: Python :: 3.6
Classifier: Programming Language :: Python :: 3.7
Classifier: Programming Language :: Python :: 3.8
Requires-Python: >=3.8
License-File: LICENSE
License-File: AUTHORS.rst
